riip/__init__.py
riip/dataframe.py
riip/material.py
riip/data/my_database/library.yml
riip/data/my_database/data/BB/Ag/Rakic.yml
riip/data/my_database/data/BB/Al/Rakic.yml
riip/data/my_database/data/BB/Au/Rakic.yml
riip/data/my_database/data/BB/Be/Rakic.yml
riip/data/my_database/data/BB/Cr/Rakic.yml
riip/data/my_database/data/BB/Cu/Rakic.yml
riip/data/my_database/data/BB/Ni/Rakic.yml
riip/data/my_database/data/BB/Pd/Rakic.yml
riip/data/my_database/data/BB/Pt/Rakic.yml
riip/data/my_database/data/BB/Ti/Rakic.yml
riip/data/my_database/data/BB/W/Rakic.yml
riip/data/my_database/data/DL/Ag/Lee.yml
riip/data/my_database/data/DL/Ag/Rakic.yml
riip/data/my_database/data/DL/Ag/Vial.yml
riip/data/my_database/data/DL/Al/Rakic.yml
riip/data/my_database/data/DL/Au/Rakic.yml
riip/data/my_database/data/DL/Au/Stewart.yml
riip/data/my_database/data/DL/Au/Vial_d.yml
riip/data/my_database/data/DL/Au/Vial_dl.yml
riip/data/my_database/data/DL/Be/Rakic.yml
riip/data/my_database/data/DL/Cr/Rakic.yml
riip/data/my_database/data/DL/Cu/Rakic.yml
riip/data/my_database/data/DL/Ni/Rakic.yml
riip/data/my_database/data/DL/Pd/Rakic.yml
riip/data/my_database/data/DL/Pt/Rakic.yml
riip/data/my_database/data/DL/Ti/Rakic.yml
riip/data/my_database/data/DL/W/Rakic.yml
riip-0.4.0.dist-info/LICENSE
riip-0.4.0.dist-info/METADATA
riip-0.4.0.dist-info/WHEEL
riip-0.4.0.dist-info/top_level.txt
riip-0.4.0.dist-info/RECORD
