Metadata-Version: 2.1
Name: riip
Version: 0.4.0
Summary: Python 3 + Pandas wrapper for the refractiveindex.info database
Home-page: https://github.com/mnishida/RII_Pandas
Author: Munehiro Nishida
Author-email: mnishida@hiroshima-u.ac.jp
License: MIT
Platform: UNKNOWN
Classifier: Development Status :: 4 - Beta
Classifier: License :: OSI Approved :: MIT License
Classifier: Programming Language :: Python
Classifier: Programming Language :: Python :: 3.7
Classifier: Programming Language :: Python :: 3.8
Classifier: Programming Language :: Python :: 3.9
Classifier: Topic :: Scientific/Engineering
Requires-Python: >=3.7
Requires-Dist: numpy (>=1.20)
Requires-Dist: scipy
Requires-Dist: pandas
Requires-Dist: tables
Requires-Dist: pyyaml
Requires-Dist: gitpython
Requires-Dist: matplotlib
Requires-Dist: ipython
Requires-Dist: ipykernel
